rdklib/__init__.py
rdklib/clientfactory.py
rdklib/configrule.py
rdklib/errors.py
rdklib/evaluation.py
rdklib/evaluator.py
rdklib/util/__init__.py
rdklib/util/evaluations.py
rdklib/util/external.py
rdklib/util/service.py
rdklibtest/__init__.py
rdklibtest/test.py
rdklib-0.3.8.dist-info/LICENSE
rdklib-0.3.8.dist-info/METADATA
rdklib-0.3.8.dist-info/NOTICE
rdklib-0.3.8.dist-info/WHEEL
rdklib-0.3.8.dist-info/RECORD
