Metadata-Version: 2.3
Name: rdklib
Version: 0.3.8
Summary: Rule Development Kit Library for AWS Config
License: Apache-2.0
Keywords: amazon,aws,awslabs,rdk,rdklib,layer,lambda,config,rules,compliance
Author: AWS RDK Maintainers
Author-email: rdk-maintainers@amazon.com
Requires-Python: >=3.7
Classifier: License :: OSI Approved :: Apache Software License
Classifier: Programming Language :: Python
Classifier: Programming Language :: Python :: 3
Classifier: Programming Language :: Python :: 3.10
Classifier: Programming Language :: Python :: 3.11
Classifier: Programming Language :: Python :: 3.12
Classifier: Programming Language :: Python :: 3.13
Classifier: Programming Language :: Python :: 3.7
Classifier: Programming Language :: Python :: 3.8
Classifier: Programming Language :: Python :: 3.9
Requires-Dist: bandit (>=1.7.7,<2.0.0)
Requires-Dist: boto3 (>=1.35.0,<2.0.0)
Requires-Dist: idna (>=3.7,<4.0)
Requires-Dist: pyyaml (>=6.0,<7.0)
Requires-Dist: rdk (>=0.17,<0.18)
Project-URL: Documentation, https://aws-config-rdklib.readthedocs.io
Project-URL: Homepage, https://github.com/awslabs/aws-config-rdklib
Project-URL: Repository, https://github.com/awslabs/aws-config-rdklib
